{
  "version": 2,
  "extractor": "pdffigures2",
  "figures": [
    {
      "url": "assets/figures/arxiv/2604.14362v1/fig-001.webp",
      "caption": "Table 8: Sample SQL Queries by Category",
      "page": 14,
      "index": 1,
      "width": 943,
      "height": 590
    },
    {
      "url": "assets/figures/arxiv/2604.14362v1/fig-002.webp",
      "caption": "Figure 1: End-to-end pipeline for constructing and querying APEX-MEM Graph, showing data flow from unstructured conversation to GraphSQL QA Agent.",
      "page": 3,
      "index": 2,
      "width": 950,
      "height": 271
    },
    {
      "url": "assets/figures/arxiv/2604.14362v1/fig-003.webp",
      "caption": "Table 13: Examples of text-to-graph conversion in APEX-MEM. Each conversational utterance is systematically transformed into structured entity-property-value triplets with appropriate semantic types, enabling sophisticated querying and temporal reasoning over conversational knowledge.",
      "page": 18,
      "index": 3,
      "width": 938,
      "height": 731
    },
    {
      "url": "assets/figures/arxiv/2604.14362v1/fig-004.webp",
      "caption": "Figure 2: Analysis of Tool Calls v/s Accuracy on LOCOMO Dataset. We cap the max Tool calls at 40.",
      "page": 13,
      "index": 4,
      "width": 933,
      "height": 440
    },
    {
      "url": "assets/figures/arxiv/2604.14362v1/fig-005.webp",
      "caption": "Table 4: LongMemEval Evaluation Results",
      "page": 8,
      "index": 5,
      "width": 945,
      "height": 375
    },
    {
      "url": "assets/figures/arxiv/2604.14362v1/fig-006.webp",
      "caption": "Figure 3: APEX-MEM Graph Structure: The figure demonstrates how conversational turns and events connect to entities through participation relationships, with temporal information preserved and entities organized by semantic type for efficient querying and reasoning.",
      "page": 19,
      "index": 6,
      "width": 848,
      "height": 599
    },
    {
      "url": "assets/figures/arxiv/2604.14362v1/fig-007.webp",
      "caption": "Figure 4: APEX-MEM Ontological Architecture: Complete structural and semantic view showing the flow from conversational sessions through temporal events to typed knowledge extraction. The diagram illustrates both table-level relationships (solid arrows) and semantic type instantiation (dashed arrows), demonstrating how the system transforms unstructured conversations into a rich, ontology-grounded knowledge graph with diverse entity types including PERSON, CREATIVE_WORK, PLACE, PRODUCT, and others.",
      "page": 20,
      "index": 7,
      "width": 913,
      "height": 670
    },
    {
      "url": "assets/figures/arxiv/2604.14362v1/fig-008.webp",
      "caption": "Table 9: Token consumption comparison across memory methods. †Accuracy depends on QnA model. ‡Tunable via top-k retrieval budget. GC = Graph/Memory Construction; Amort. = Amortized over queries per conversation.",
      "page": 16,
      "index": 8,
      "width": 937,
      "height": 279
    },
    {
      "url": "assets/figures/arxiv/2604.14362v1/fig-009.webp",
      "caption": "Table 10: APEX-MEM token decomposition per query.",
      "page": 16,
      "index": 9,
      "width": 451,
      "height": 269
    }
  ]
}